probspellchecker/__init__.py
probspellchecker-0.1.3.data/scripts/probdict-from-dewiki.py
probspellchecker-0.1.3.data/scripts/probdict-from-text.py
probspellchecker-0.1.3.dist-info/METADATA
probspellchecker-0.1.3.dist-info/RECORD
probspellchecker-0.1.3.dist-info/WHEEL
probspellchecker-0.1.3.dist-info/top_level.txt
