Metadata-Version: 2.1
Name: probspellchecker
Version: 0.1.3
Summary: probabilistic spell checker
Home-page: https://github.com/digitalarbeiter/probspellchecker
Author: digitalarbeiter
Author-email: digitalarbeiter@talbriefkasten.de
License: LGPLv3
Platform: UNKNOWN
